kllrr/__init__.py
kllrr/kllrr.py
kllrr-0.1.dist-info/METADATA
kllrr-0.1.dist-info/WHEEL
kllrr-0.1.dist-info/top_level.txt
kllrr-0.1.dist-info/RECORD
