Metadata-Version: 2.1
Name: kllrr
Version: 0.1
Summary: The Goal Of This Library Is To Help Students To Learn programming
